[
    {
        "id": "node/2488918181",
        "coordinates": [
            -37.5671965,
            -6.7386901
        ],
        "connections": [
            {
                "id": "node/2488918194",
                "coordinates": [
                    -37.5670356,
                    -6.7381268
                ]
            },
            {
                "id": "node/2494525044",
                "coordinates": [
                    -37.5676022,
                    -6.7386422
                ]
            },
            {
                "id": "node/7641883286",
                "coordinates": [
                    -37.5672568,
                    -6.7388859
                ]
            },
            {
                "id": "node/8441594820",
                "coordinates": [
                    -37.5663062,
                    -6.7388817
                ]
            }
        ]
    },
    {
        "id": "node/2488918193",
        "coordinates": [
            -37.5694792,
            -6.7377038
        ],
        "connections": [
            {
                "id": "node/2488918195",
                "coordinates": [
                    -37.5694951,
                    -6.7377865
                ]
            },
            {
                "id": "node/2488918196",
                "coordinates": [
                    -37.5694153,
                    -6.7373278
                ]
            },
            {
                "id": "node/2494517082",
                "coordinates": [
                    -37.5690625,
                    -6.7377677
                ]
            }
        ]
    },
    {
        "id": "node/2488918194",
        "coordinates": [
            -37.5670356,
            -6.7381268
        ],
        "connections": [
            {
                "id": "node/2488918181",
                "coordinates": [
                    -37.5671965,
                    -6.7386901
                ]
            },
            {
                "id": "node/2488918192",
                "coordinates": [
                    -37.5670009,
                    -6.7380422
                ]
            },
            {
                "id": "node/2494525045",
                "coordinates": [
                    -37.5674473,
                    -6.7380715
                ]
            }
        ]
    },
    {
        "id": "node/2488918197",
        "coordinates": [
            -37.5672682,
            -6.7376541
        ],
        "connections": [
            {
                "id": "node/2488918201",
                "coordinates": [
                    -37.5676622,
                    -6.7375723
                ]
            }
        ]
    },
    {
        "id": "node/2488918198",
        "coordinates": [
            -37.5685663,
            -6.7368883
        ],
        "connections": [
            {
                "id": "node/2488918200",
                "coordinates": [
                    -37.5675784,
                    -6.7370842
                ]
            }
        ]
    },
    {
        "id": "node/2488918201",
        "coordinates": [
            -37.5676622,
            -6.7375723
        ],
        "connections": [
            {
                "id": "node/2488918197",
                "coordinates": [
                    -37.5672682,
                    -6.7376541
                ]
            },
            {
                "id": "node/2494525037",
                "coordinates": [
                    -37.5678389,
                    -6.7375361
                ]
            },
            {
                "id": "node/7642981733",
                "coordinates": [
                    -37.5676106,
                    -6.7372653
                ]
            }
        ]
    },
    {
        "id": "",
        "coordinates": [],
        "connections": [
            {
                "id": "node/2494517057",
                "coordinates": [
                    -37.5694428,
                    -6.7426577
                ]
            }
        ]
    },
    {
        "id": "node/2494525013",
        "coordinates": [
            -37.5699183,
            -6.7406226
        ],
        "connections": [
            {
                "id": "node/2494525009",
                "coordinates": [
                    -37.5699934,
                    -6.7410808
                ]
            },
            {
                "id": "node/2494525017",
                "coordinates": [
                    -37.5698505,
                    -6.7401341
                ]
            },
            {
                "id": "node/7642762406",
                "coordinates": [
                    -37.5697641,
                    -6.7406552
                ]
            }
        ]
    },
    {
        "id": "",
        "coordinates": [],
        "connections": []
    },
    {
        "id": "node/2494517058",
        "coordinates": [
            -37.5679287,
            -6.7431012
        ],
        "connections": [
            {
                "id": "node/2494517059",
                "coordinates": [
                    -37.5677951,
                    -6.7422625
                ]
            },
            {
                "id": "node/2494517063",
                "coordinates": [
                    -37.568256,
                    -6.7430532
                ]
            }
        ]
    },
    {
        "id": "node/2494517060",
        "coordinates": [
            -37.5692631,
            -6.7419624
        ],
        "connections": [
            {
                "id": "node/2488918207",
                "coordinates": [
                    -37.5692041,
                    -6.741732
                ]
            },
            {
                "id": "node/2494517074",
                "coordinates": [
                    -37.5687642,
                    -6.7420437
                ]
            },
            {
                "id": "node/8441594487",
                "coordinates": [
                    -37.5693951,
                    -6.7424731
                ]
            }
        ]
    },
    {
        "id": "node/2488918205",
        "coordinates": [
            -37.5685449,
            -6.7393069
        ],
        "connections": [
            {
                "id": "node/2488918206",
                "coordinates": [
                    -37.5686261,
                    -6.7395758
                ]
            },
            {
                "id": "node/2494525040",
                "coordinates": [
                    -37.5680726,
                    -6.7393682
                ]
            },
            {
                "id": "node/2494525041",
                "coordinates": [
                    -37.5684043,
                    -6.7386476
                ]
            }
        ]
    },
    {
        "id": "node/7643558945",
        "coordinates": [
            -37.5688407,
            -6.7424526
        ],
        "connections": [
            {
                "id": "node/2494517074",
                "coordinates": [
                    -37.5687642,
                    -6.7420437
                ]
            },
            {
                "id": "node/2494525007",
                "coordinates": [
                    -37.5689028,
                    -6.7427843
                ]
            },
            {
                "id": "node/7643558944",
                "coordinates": [
                    -37.5687428,
                    -6.7424253
                ]
            }
        ]
    },
    {
        "id": "",
        "coordinates": [],
        "connections": []
    },
    {
        "id": "node/2494517068",
        "coordinates": [
            -37.5691133,
            -6.7427384
        ],
        "connections": [
            {
                "id": "node/2494517057",
                "coordinates": [
                    -37.5694428,
                    -6.7426577
                ]
            },
            {
                "id": "node/2494525007",
                "coordinates": [
                    -37.5689028,
                    -6.7427843
                ]
            }
        ]
    },
    {
        "id": "node/2494517075",
        "coordinates": [
            -37.5683738,
            -6.7396419
        ],
        "connections": [
            {
                "id": "node/2488918206",
                "coordinates": [
                    -37.5686261,
                    -6.7395758
                ]
            },
            {
                "id": "node/2494517076",
                "coordinates": [
                    -37.568102,
                    -6.7396724
                ]
            },
            {
                "id": "node/7642146923",
                "coordinates": [
                    -37.5684705,
                    -6.7402271
                ]
            }
        ]
    },
    {
        "id": "node/2488918206",
        "coordinates": [
            -37.5686261,
            -6.7395758
        ],
        "connections": [
            {
                "id": "node/2488918205",
                "coordinates": [
                    -37.5685449,
                    -6.7393069
                ]
            },
            {
                "id": "node/2494517075",
                "coordinates": [
                    -37.5683738,
                    -6.7396419
                ]
            },
            {
                "id": "node/7643558931",
                "coordinates": [
                    -37.5687924,
                    -6.7401258
                ]
            }
        ]
    },
    {
        "id": "node/2494517077",
        "coordinates": [
            -37.5683015,
            -6.7416473
        ],
        "connections": [
            {
                "id": "node/2494517079",
                "coordinates": [
                    -37.5686999,
                    -6.7415962
                ]
            },
            {
                "id": "node/2494517080",
                "coordinates": [
                    -37.5680172,
                    -6.7416921
                ]
            },
            {
                "id": "node/7642146932",
                "coordinates": [
                    -37.568142,
                    -6.7405647
                ]
            }
        ]
    },
    {
        "id": "node/8441594489",
        "coordinates": [
            -37.5673523,
            -6.7418011
        ],
        "connections": [
            {
                "id": "node/2494517081",
                "coordinates": [
                    -37.5677108,
                    -6.7417421
                ]
            }
        ]
    },
    {
        "id": "node/2494517084",
        "coordinates": [
            -37.569638,
            -6.7415929
        ],
        "connections": [
            {
                "id": "node/7645379088",
                "coordinates": [
                    -37.5696259,
                    -6.7416488
                ]
            },
            {
                "id": "node/7645379089",
                "coordinates": [
                    -37.5696115,
                    -6.7414091
                ]
            }
        ]
    },
    {
        "id": "node/2494517084",
        "coordinates": [
            -37.569638,
            -6.7415929
        ],
        "connections": [
            {
                "id": "node/7645379088",
                "coordinates": [
                    -37.5696259,
                    -6.7416488
                ]
            },
            {
                "id": "node/7645379089",
                "coordinates": [
                    -37.5696115,
                    -6.7414091
                ]
            }
        ]
    },
    {
        "id": "node/2494525009",
        "coordinates": [
            -37.5699934,
            -6.7410808
        ],
        "connections": [
            {
                "id": "node/2494517053",
                "coordinates": [
                    -37.5700603,
                    -6.7415318
                ]
            },
            {
                "id": "node/2494525008",
                "coordinates": [
                    -37.5695662,
                    -6.7411423
                ]
            },
            {
                "id": "node/2494525013",
                "coordinates": [
                    -37.5699183,
                    -6.7406226
                ]
            }
        ]
    },
    {
        "id": "node/2494525013",
        "coordinates": [
            -37.5699183,
            -6.7406226
        ],
        "connections": [
            {
                "id": "node/2494525009",
                "coordinates": [
                    -37.5699934,
                    -6.7410808
                ]
            },
            {
                "id": "node/2494525017",
                "coordinates": [
                    -37.5698505,
                    -6.7401341
                ]
            },
            {
                "id": "node/7642762406",
                "coordinates": [
                    -37.5697641,
                    -6.7406552
                ]
            }
        ]
    },
    {
        "id": "node/2494525022",
        "coordinates": [
            -37.5709274,
            -6.7395045
        ],
        "connections": [
            {
                "id": "node/2494525018",
                "coordinates": [
                    -37.5709691,
                    -6.7399577
                ]
            },
            {
                "id": "node/2494525026",
                "coordinates": [
                    -37.5708637,
                    -6.7390477
                ]
            },
            {
                "id": "node/7645379087",
                "coordinates": [
                    -37.5706037,
                    -6.7395466
                ]
            }
        ]
    },
    {
        "id": "node/2494525026",
        "coordinates": [
            -37.5708637,
            -6.7390477
        ],
        "connections": [
            {
                "id": "node/2494525022",
                "coordinates": [
                    -37.5709274,
                    -6.7395045
                ]
            },
            {
                "id": "node/2494525025",
                "coordinates": [
                    -37.5696781,
                    -6.7391837
                ]
            },
            {
                "id": "node/7642762453",
                "coordinates": [
                    -37.5708537,
                    -6.7389951
                ]
            }
        ]
    },
    {
        "id": "node/2494525030",
        "coordinates": [
            -37.5707504,
            -6.7386335
        ],
        "connections": [
            {
                "id": "node/2494525029",
                "coordinates": [
                    -37.5696252,
                    -6.7387729
                ]
            },
            {
                "id": "node/7642762447",
                "coordinates": [
                    -37.5707209,
                    -6.7383945
                ]
            },
            {
                "id": "node/7642762448",
                "coordinates": [
                    -37.5707652,
                    -6.7386795
                ]
            }
        ]
    },
    {
        "id": "node/2494525034",
        "coordinates": [
            -37.570686,
            -6.7381441
        ],
        "connections": [
            {
                "id": "node/2494525033",
                "coordinates": [
                    -37.5695556,
                    -6.7382916
                ]
            },
            {
                "id": "node/2494525035",
                "coordinates": [
                    -37.5706176,
                    -6.7377219
                ]
            },
            {
                "id": "node/7642762446",
                "coordinates": [
                    -37.5707196,
                    -6.7383945
                ]
            }
        ]
    },
    {
        "id": "node/2494525035",
        "coordinates": [
            -37.5706176,
            -6.7377219
        ],
        "connections": [
            {
                "id": "node/2494525034",
                "coordinates": [
                    -37.570686,
                    -6.7381441
                ]
            },
            {
                "id": "node/7642762461",
                "coordinates": [
                    -37.5705895,
                    -6.7376946
                ]
            }
        ]
    },
    {
        "id": "node/2494525018",
        "coordinates": [
            -37.5709691,
            -6.7399577
        ],
        "connections": [
            {
                "id": "node/2494525022",
                "coordinates": [
                    -37.5709274,
                    -6.7395045
                ]
            },
            {
                "id": "node/7643639701",
                "coordinates": [
                    -37.5709767,
                    -6.739989
                ]
            }
        ]
    },
    {
        "id": "node/8441594490",
        "coordinates": [
            -37.5681771,
            -6.7403798
        ],
        "connections": [
            {
                "id": "node/2494517076",
                "coordinates": [
                    -37.568102,
                    -6.7396724
                ]
            },
            {
                "id": "node/7642146928",
                "coordinates": [
                    -37.5681849,
                    -6.7403672
                ]
            },
            {
                "id": "node/7642146929",
                "coordinates": [
                    -37.5681621,
                    -6.7404042
                ]
            }
        ]
    },
    {
        "id": "node/2494525042",
        "coordinates": [
            -37.5679973,
            -6.7387055
        ],
        "connections": [
            {
                "id": "node/2494525040",
                "coordinates": [
                    -37.5680726,
                    -6.7393682
                ]
            },
            {
                "id": "node/2494525041",
                "coordinates": [
                    -37.5684043,
                    -6.7386476
                ]
            },
            {
                "id": "node/2494525043",
                "coordinates": [
                    -37.5679832,
                    -6.7386059
                ]
            }
        ]
    },
    {
        "id": "node/2488918181",
        "coordinates": [
            -37.5671965,
            -6.7386901
        ],
        "connections": [
            {
                "id": "node/2488918194",
                "coordinates": [
                    -37.5670356,
                    -6.7381268
                ]
            },
            {
                "id": "node/2494525044",
                "coordinates": [
                    -37.5676022,
                    -6.7386422
                ]
            },
            {
                "id": "node/7641883286",
                "coordinates": [
                    -37.5672568,
                    -6.7388859
                ]
            },
            {
                "id": "node/8441594820",
                "coordinates": [
                    -37.5663062,
                    -6.7388817
                ]
            }
        ]
    },
    {
        "id": "node/2494525046",
        "coordinates": [
            -37.5674211,
            -6.7379949
        ],
        "connections": [
            {
                "id": "node/2488918192",
                "coordinates": [
                    -37.5670009,
                    -6.7380422
                ]
            },
            {
                "id": "node/2494525038",
                "coordinates": [
                    -37.5678925,
                    -6.7379296
                ]
            },
            {
                "id": "node/2494525045",
                "coordinates": [
                    -37.5674473,
                    -6.7380715
                ]
            }
        ]
    },
    {
        "id": "node/2494525048",
        "coordinates": [
            -37.5679682,
            -6.7384494
        ],
        "connections": [
            {
                "id": "node/2494525039",
                "coordinates": [
                    -37.5678992,
                    -6.7380029
                ]
            },
            {
                "id": "node/2494525043",
                "coordinates": [
                    -37.5679832,
                    -6.7386059
                ]
            },
            {
                "id": "node/2494525047",
                "coordinates": [
                    -37.56758,
                    -6.7385476
                ]
            }
        ]
    },
    {
        "id": "node/2494525049",
        "coordinates": [
            -37.5660854,
            -6.7389292
        ],
        "connections": [
            {
                "id": "node/2903627978",
                "coordinates": [
                    -37.5657763,
                    -6.7390204
                ]
            },
            {
                "id": "node/8441594820",
                "coordinates": [
                    -37.5663062,
                    -6.7388817
                ]
            }
        ]
    },
    {
        "id": "",
        "coordinates": [],
        "connections": []
    },
    {
        "id": "",
        "coordinates": [],
        "connections": []
    },
    {
        "id": "",
        "coordinates": [],
        "connections": []
    },
    {
        "id": "node/7643519696",
        "coordinates": [
            -37.5708141,
            -6.7399682
        ],
        "connections": [
            {
                "id": "node/2494525017",
                "coordinates": [
                    -37.5698505,
                    -6.7401341
                ]
            },
            {
                "id": "node/7645374682",
                "coordinates": [
                    -37.5707974,
                    -6.739942
                ]
            },
            {
                "id": "node/7645374683",
                "coordinates": [
                    -37.5708356,
                    -6.740002
                ]
            }
        ]
    },
    {
        "id": "node/2488918182",
        "coordinates": [
            -37.5667102,
            -6.7372412
        ],
        "connections": [
            {
                "id": "node/2488918192",
                "coordinates": [
                    -37.5670009,
                    -6.7380422
                ]
            },
            {
                "id": "node/2488918200",
                "coordinates": [
                    -37.5675784,
                    -6.7370842
                ]
            }
        ]
    },
    {
        "id": "node/2494517080",
        "coordinates": [
            -37.5680172,
            -6.7416921
        ],
        "connections": [
            {
                "id": "node/2494517061",
                "coordinates": [
                    -37.567711,
                    -6.7394152
                ]
            },
            {
                "id": "node/2494517077",
                "coordinates": [
                    -37.5683015,
                    -6.7416473
                ]
            },
            {
                "id": "node/2494517081",
                "coordinates": [
                    -37.5677108,
                    -6.7417421
                ]
            },
            {
                "id": "node/7643558933",
                "coordinates": [
                    -37.5680736,
                    -6.7419025
                ]
            }
        ]
    },
    {
        "id": "node/7272074392",
        "coordinates": [
            -37.5717482,
            -6.742057
        ],
        "connections": [
            {
                "id": "node/7272074393",
                "coordinates": [
                    -37.571716,
                    -6.7418759
                ]
            }
        ]
    },
    {
        "id": "",
        "coordinates": [],
        "connections": [
            {
                "id": "node/2494517064",
                "coordinates": [
                    -37.5683276,
                    -6.7436188
                ]
            },
            {
                "id": "node/7642125026",
                "coordinates": [
                    -37.5684571,
                    -6.7436672
                ]
            }
        ]
    },
    {
        "id": "node/7642125038",
        "coordinates": [
            -37.5690104,
            -6.7437165
        ],
        "connections": [
            {
                "id": "node/7642125031",
                "coordinates": [
                    -37.5689627,
                    -6.7436932
                ]
            },
            {
                "id": "node/7642125044",
                "coordinates": [
                    -37.5688735,
                    -6.7429007
                ]
            }
        ]
    },
    {
        "id": "node/2494517064",
        "coordinates": [
            -37.5683276,
            -6.7436188
        ],
        "connections": [
            {
                "id": "node/7642125046",
                "coordinates": [
                    -37.5686918,
                    -6.7430772
                ]
            }
        ]
    },
    {
        "id": "node/2494517053",
        "coordinates": [
            -37.5700603,
            -6.7415318
        ],
        "connections": [
            {
                "id": "node/2494525009",
                "coordinates": [
                    -37.5699934,
                    -6.7410808
                ]
            },
            {
                "id": "node/7642741084",
                "coordinates": [
                    -37.5700674,
                    -6.741598
                ]
            }
        ]
    },
    {
        "id": "node/2494517053",
        "coordinates": [
            -37.5700603,
            -6.7415318
        ],
        "connections": [
            {
                "id": "node/2494525009",
                "coordinates": [
                    -37.5699934,
                    -6.7410808
                ]
            },
            {
                "id": "node/7642741084",
                "coordinates": [
                    -37.5700674,
                    -6.741598
                ]
            }
        ]
    },
    {
        "id": "node/2494525036",
        "coordinates": [
            -37.5712252,
            -6.7416428
        ],
        "connections": [
            {
                "id": "node/2494525010",
                "coordinates": [
                    -37.571078,
                    -6.740948
                ]
            },
            {
                "id": "node/7642762436",
                "coordinates": [
                    -37.571248,
                    -6.741764
                ]
            }
        ]
    },
    {
        "id": "",
        "coordinates": [],
        "connections": []
    },
    {
        "id": "node/2494525009",
        "coordinates": [
            -37.5699934,
            -6.7410808
        ],
        "connections": [
            {
                "id": "node/2494517053",
                "coordinates": [
                    -37.5700603,
                    -6.7415318
                ]
            },
            {
                "id": "node/2494525008",
                "coordinates": [
                    -37.5695662,
                    -6.7411423
                ]
            },
            {
                "id": "node/2494525013",
                "coordinates": [
                    -37.5699183,
                    -6.7406226
                ]
            }
        ]
    },
    {
        "id": "node/7643639699",
        "coordinates": [
            -37.5686677,
            -6.737887
        ],
        "connections": [
            {
                "id": "node/2488918204",
                "coordinates": [
                    -37.5682881,
                    -6.737947
                ]
            },
            {
                "id": "node/2494517083",
                "coordinates": [
                    -37.5690751,
                    -6.7378509
                ]
            },
            {
                "id": "node/7643639700",
                "coordinates": [
                    -37.5686574,
                    -6.7378265
                ]
            }
        ]
    },
    {
        "id": "node/7645379087",
        "coordinates": [
            -37.5706037,
            -6.7395466
        ],
        "connections": [
            {
                "id": "node/2494525021",
                "coordinates": [
                    -37.5697665,
                    -6.7396554
                ]
            },
            {
                "id": "node/2494525022",
                "coordinates": [
                    -37.5709274,
                    -6.7395045
                ]
            },
            {
                "id": "node/7645374682",
                "coordinates": [
                    -37.5707974,
                    -6.739942
                ]
            }
        ]
    },
    {
        "id": "node/2494517078",
        "coordinates": [
            -37.5691532,
            -6.7415229
        ],
        "connections": [
            {
                "id": "node/2488918207",
                "coordinates": [
                    -37.5692041,
                    -6.741732
                ]
            },
            {
                "id": "node/2494517079",
                "coordinates": [
                    -37.5686999,
                    -6.7415962
                ]
            },
            {
                "id": "node/7643558932",
                "coordinates": [
                    -37.5689976,
                    -6.740849
                ]
            },
            {
                "id": "node/7645379089",
                "coordinates": [
                    -37.5696115,
                    -6.7414091
                ]
            }
        ]
    },
    {
        "id": "node/7642762407",
        "coordinates": [
            -37.571826,
            -6.7406373
        ],
        "connections": [
            {
                "id": "node/3964600243",
                "coordinates": [
                    -37.5716811,
                    -6.7403829
                ]
            },
            {
                "id": "node/3964600247",
                "coordinates": [
                    -37.5721411,
                    -6.7404521
                ]
            },
            {
                "id": "node/7642762405",
                "coordinates": [
                    -37.5716013,
                    -6.7406626
                ]
            },
            {
                "id": "node/7643503901",
                "coordinates": [
                    -37.5718783,
                    -6.7407278
                ]
            }
        ]
    },
    {
        "id": "node/8441594486",
        "coordinates": [
            -37.5703149,
            -6.7432668
        ],
        "connections": []
    },
    {
        "id": "node/8441594488",
        "coordinates": [
            -37.5697158,
            -6.742403
        ],
        "connections": [
            {
                "id": "node/2494517054",
                "coordinates": [
                    -37.5696057,
                    -6.7418941
                ]
            },
            {
                "id": "node/2494517056",
                "coordinates": [
                    -37.5697567,
                    -6.7425924
                ]
            },
            {
                "id": "node/8441594487",
                "coordinates": [
                    -37.5693951,
                    -6.7424731
                ]
            }
        ]
    }
]